tkdm/__init__.py
tkdm/autogallery.py
tkdm/genautoindex.py
tkdm/util.py
tkdm-0.1.1.dist-info/entry_points.txt
tkdm-0.1.1.dist-info/WHEEL
tkdm-0.1.1.dist-info/METADATA
tkdm-0.1.1.dist-info/RECORD
