Metadata-Version: 2.1
Name: tkdm
Version: 0.1.1
Summary: kdm9's toolkit
Author-email: "K. D. Murray" <info@gekkonid.com>
Requires-Python: >=3.9
Requires-Dist: tqdm
Requires-Dist: pillow
Requires-Dist: heif-image-plugin
